MANIFEST.in
README.md
install.json
package.json
pyproject.toml
react_editable_table.json
setup.cfg
setup.py
tsconfig.json
webpack.config.js
examples/introduction.ipynb
react_editable_table/__init__.py
react_editable_table/_frontend.py
react_editable_table/_version.py
react_editable_table/widget.py
react_editable_table.egg-info/PKG-INFO
react_editable_table.egg-info/SOURCES.txt
react_editable_table.egg-info/dependency_links.txt
react_editable_table.egg-info/requires.txt
react_editable_table.egg-info/top_level.txt
react_editable_table/labextension/build_log.json
react_editable_table/labextension/package.json
react_editable_table/labextension/static/lib_index_js.e6966c837e725382f93e.js
react_editable_table/labextension/static/lib_index_js.e6966c837e725382f93e.js.map
react_editable_table/labextension/static/lib_plugin_js.1e650cc31d573daec095.js
react_editable_table/labextension/static/lib_plugin_js.1e650cc31d573daec095.js.map
react_editable_table/labextension/static/lib_widget_js.e581d1c3446a69e4da81.js
react_editable_table/labextension/static/lib_widget_js.e581d1c3446a69e4da81.js.map
react_editable_table/labextension/static/remoteEntry.33176020e90c68450293.js
react_editable_table/labextension/static/remoteEntry.33176020e90c68450293.js.map
react_editable_table/labextension/static/style.js
react_editable_table/labextension/static/vendors-node_modules_mantine_core_esm_index_js-node_modules_ahooks_es_index_js-node_modules_i-d1af73.0f5a02a624163810708e.js
react_editable_table/labextension/static/vendors-node_modules_mantine_core_esm_index_js-node_modules_ahooks_es_index_js-node_modules_i-d1af73.0f5a02a624163810708e.js.map
react_editable_table/nbextension/extension.js
react_editable_table/nbextension/index.js
react_editable_table/nbextension/index.js.LICENSE.txt
react_editable_table/nbextension/index.js.map
src/extension.ts
src/index.ts
src/plugin.ts
src/version.ts
src/widget.ts
src/react/ReactEditableTable.tsx
src/react/model.ts