Metadata-Version: 2.1
Name: react-editable-table
Version: 0.0.2
Summary: A Custom Jupyter Widget Library
Home-page: https://github.com/tidbcloud/react-editable-table
Author: zoubingwu
Author-email: zoubingwu@gmail.com
License: BSD
Keywords: Jupyter,Widgets,IPython
Platform: Linux
Platform: Mac OS X
Platform: Windows
Classifier: Intended Audience :: Developers
Classifier: Intended Audience :: Science/Research
Classifier: License :: OSI Approved :: BSD License
Classifier: Programming Language :: Python
Classifier: Programming Language :: Python :: 3
Classifier: Programming Language :: Python :: 3.4
Classifier: Programming Language :: Python :: 3.5
Classifier: Programming Language :: Python :: 3.6
Classifier: Programming Language :: Python :: 3.7
Classifier: Framework :: Jupyter
Requires-Python: >=3.6
Provides-Extra: test
Provides-Extra: examples
Provides-Extra: docs
